_tenseal_cpp.cpython-39-x86_64-linux-gnu.so
libtenseal.so
_sealapi_cpp.cpython-39-x86_64-linux-gnu.so
tenseal-0.3.14.dist-info/RECORD
tenseal-0.3.14.dist-info/METADATA
tenseal-0.3.14.dist-info/top_level.txt
tenseal-0.3.14.dist-info/LICENSE
tenseal-0.3.14.dist-info/WHEEL
tenseal/__init__.py
tenseal/version.py
tenseal/enc_context.py
tenseal/sealapi/__init__.py
tenseal/sealapi/util/__init__.py
tenseal/tensors/bfvtensor.py
tenseal/tensors/__init__.py
tenseal/tensors/plaintensor.py
tenseal/tensors/ckksvector.py
tenseal/tensors/bfvvector.py
tenseal/tensors/abstract_tensor.py
tenseal/tensors/ckkstensor.py
