Metadata-Version: 2.1
Name: tenseal
Version: 0.3.14
Summary: A Library for Homomorphic Encryption Operations on Tensors
Home-page: https://github.com/OpenMined/TenSEAL
Author: OpenMined
Author-email: info@openmined.org
License: Apache-2.0
Keywords: homomorphic encryption tensor deep learning privacy secure
Classifier: Programming Language :: C++
Classifier: Programming Language :: Python :: 3
Classifier: Operating System :: OS Independent
Classifier: Topic :: Security :: Cryptography
License-File: LICENSE
